Examples/__init__.py
Examples/demo.py
Tutorials/__init__.py
deepdream-2020.4.10.15.52.41.dist-info/METADATA
deepdream-2020.4.10.15.52.41.dist-info/RECORD
deepdream-2020.4.10.15.52.41.dist-info/WHEEL
deepdream-2020.4.10.15.52.41.dist-info/entry_points.txt
deepdream-2020.4.10.15.52.41.dist-info/top_level.txt
deeps/Require.md
deeps/__init__.py
deeps/backend.py
deeps/demo.py
deeps/files.yml
deeps/activations/__init__.py
deeps/callbacks/__init__.py
deeps/callbacks/wandb_callback.py
deeps/cv/KerasCV.py
deeps/cv/__init__.py
deeps/dateset/DataLoader.py
deeps/dateset/__init__.py
deeps/dateset/utils.py
deeps/deploy/README.md
deeps/deploy/__init__.py
deeps/deploy/serving/__init__.py
deeps/deploy/serving/onnx/__init__.py
deeps/deploy/serving/onnx/gbtree.onnx
deeps/deploy/serving/onnx/inference.py
deeps/deploy/serving/onnx/iris.onnx
deeps/deploy/serving/onnx/simplifier_onnx.sh
deeps/deploy/serving/onnx/torch_convert.py
deeps/deploy/serving/onnx/xgb_convert.py
deeps/layers/DNN.py
deeps/layers/__init__.py
deeps/learn_rate/__init__.py
deeps/learn_rate/clr/CyclicLR.py
deeps/learn_rate/clr/__init__.py
deeps/losses/__init__.py
deeps/metrics/F1Optimizer.py
deeps/metrics/__init__.py
deeps/metrics/expected_f1.png
deeps/metrics/runtimes.png
deeps/metrics/shake.py
deeps/models/README.md
deeps/models/__init__.py
deeps/models/fc.py
deeps/optimizers/__init__.py
deeps/tricks/Adversarialvalidation.py
deeps/tricks/CalibratedClassifierCV.py
deeps/tricks/__init__.py
deeps/tricks/online_info/__init__.py
deeps/tricks/online_info/get_label.py
deeps/utils/__init__.py
deeps/utils/cprint.py
deeps/utils/tfreader.py
deeps/utils/timer.py
deeps/utils/torch_.py
